bstk_datatables/__init__.py
bstk_datatables/entry.py
bstk_datatables/enum.py
bstk_datatables/schema.py
bstk_datatables/table.py
bstk_datatables/validators/luhn.py
bstk_datatables-0.3.1.dist-info/METADATA
bstk_datatables-0.3.1.dist-info/WHEEL
bstk_datatables-0.3.1.dist-info/RECORD
