Metadata-Version: 2.1
Name: bstk-datatables
Version: 0.3.1
Summary: A polymorphic schema managed semi structured crosslinked data dictionary builder.. BINGO!
License: MIT
Author: colin
Author-email: colin@broadstack.com.au
Requires-Python: >=3.8,<4.0
Classifier: License :: OSI Approved :: MIT License
Classifier: Programming Language :: Python :: 3
Classifier: Programming Language :: Python :: 3.8
Classifier: Programming Language :: Python :: 3.9
Classifier: Programming Language :: Python :: 3.10
Classifier: Programming Language :: Python :: 3.11
Requires-Dist: marshmallow (>=3.19.0,<4.0.0)
Requires-Dist: typing_extensions (>=4.5.0,<5.0.0) ; python_version < "3.10"
